voxline/__init__.py
voxline/models.py
voxline/api/__init__.py
voxline/api/activity.py
voxline/api/form.py
voxline/api/memo.py
voxline/api/request.py
voxline/api/shift.py
voxline/api/user.py
voxline_pdk-1.0.1.dist-info/METADATA
voxline_pdk-1.0.1.dist-info/WHEEL
voxline_pdk-1.0.1.dist-info/top_level.txt
voxline_pdk-1.0.1.dist-info/RECORD
