Metadata-Version: 2.1
Name: voxline-pdk
Version: 1.0.1
Summary: sdk to connect with voxline
Author: inndico
License: MIT
